Workbook

Sheet Dashboard
B2: GLA UNIVERSITY, MATHURA
B3: 32-Class DSA Pattern Mastery Program - HackerRank + Codeforces (Non-LeetCode)
B6: PROGRAM AT A GLANCE
B7: Total Classes | C7: 32 (5 hours each = 160 contact hours)
B8: Per Class | C8: 5 questions discussed in class + 10 homework questions
B9: Total Questions | C9: 480 (160 in-class + 320 homework)
B10: Platforms | C10: HackerRank + Codeforces only (no LeetCode)
B11: Coverage | C11: All DSA patterns, start to finish - Arrays to DP, Big-O as capstone
B12: Difficulty | C12: Progressive: HR Easy / CF 800 in Class 1 → CF 1600 by Class 32
B14: LIVE PROGRESS (auto-updates from Tracker)
B15: Questions Solved | C15: =COUNTIF(Tracker!$J:$J,"Solved") -> 11 | D15: of 480
B16: Questions Attempted | C16: =COUNTIF(Tracker!$J:$J,"Attempted") -> 0
B17: Questions Revised | C17: =COUNTIF(Tracker!$J:$J,"Revised") -> 0
B18: In-Class Solved | C18: =COUNTIFS(Tracker!$B:$B,"In-Class",Tracker!$J:$J,"Solved") -> 5 | D18: of 160
B19: Homework Solved | C19: =COUNTIFS(Tracker!$B:$B,"Homework",Tracker!$J:$J,"Solved") -> 6 | D19: of 320
B20: Overall Completion % | C20: =ROUND(COUNTIF(Tracker!$J:$J,"Solved")/480*100,1)&"%" -> 2.3%
B22: HOW TO USE (Legend)
B23: 1. Only edit the Status and Notes columns (J and K) in the Tracker sheet - yellow-tinted cells.
B24: 2. Status dropdown: Not Started → Attempted → Solved → Revised. Everything else auto-calculates.
B25: 3. Row 2 of the Tracker is pre-filled with 'Solved' as an example - update it as you actually progress.
B26: 4. Class Plan sheet shows per-class completion; Pattern Guide explains every pattern's what/spot/why.
B27: 5. Click any link in column H to open the problem directly on HackerRank / Codeforces.

Sheet Class Plan
A1: CLASS PLAN - 32 Classes × 5 Hours | 5 In-Class + 10 Homework Each
A2: Class # | B2: Pattern / Topic | C2: Difficulty Band | D2: In-Class Done (of 5) | E2: Homework Done (of 10) | F2: Total Done (of 15) | G2: Completion % | H2: Status | I2: Suggested Hour Split (5 hrs)
A3: 1 | B3: Arrays & Implementation Basics | C3: HR Easy / CF 800-900 | D3: 4 | E3: 1 | F3: =D3+E3 -> 5 | G3: =ROUND(F3/15*100,0)&"%" -> 33% | H3: =IF(F3=15,"Complete",IF(F3=0,"Not Started","In Progress")) -> In Progress | I3: 1.0 hr concept + 2.5 hrs solving 5 class Qs + 1.0 hr pattern recap + 0.5 hr HW briefing
A4: 2 | B4: Prefix Sums & Difference Arrays | C4: HR Easy-Hard / CF 1100-1400 | D4: 3 | E4: =COUNTIFS(Tracker!$A:$A,2,Tracker!$B:$B,"Homework",Tracker!$J:$J,"Solved") -> 0 | F4: =D4+E4 -> 3 | G4: =ROUND(F4/15*100,0)&"%" -> 20% | H4: Solved | I4: 1.0 hr concept + 2.5 hrs solving 5 class Qs + 1.0 hr pattern recap + 0.5 hr HW briefing
A5: 3 | B5: Two Pointers I - Converging & Parallel Scans | C5: CF 800-1100 | D5: =COUNTIFS(Tracker!$A:$A,3,Tracker!$B:$B,"In-Class",Tracker!$J:$J,"Solved") -> 0 | E5: =COUNTIFS(Tracker!$A:$A,3,Tracker!$B:$B,"Homework",Tracker!$J:$J,"Solved") -> 0 | F5: =D5+E5 -> 0 | G5: =ROUND(F5/15*100,0)&"%" -> 0% | H5: =IF(F5=15,"Complete",IF(F5=0,"Not Started","In Progress")) -> Not Started | I5: 1.0 hr concept + 2.5 hrs solving 5 class Qs + 1.0 hr pattern recap + 0.5 hr HW briefing
A6: 4 | B6: Sliding Window - Fixed Size | C6: HR Easy-Med / CF 1000-1200 | D6: =COUNTIFS(Tracker!$A:$A,4,Tracker!$B:$B,"In-Class",Tracker!$J:$J,"Solved") -> 0 | E6: =COUNTIFS(Tracker!$A:$A,4,Tracker!$B:$B,"Homework",Tracker!$J:$J,"Solved") -> 0 | F6: =D6+E6 -> 0 | G6: =ROUND(F6/15*100,0)&"%" -> 0% | H6: =IF(F6=15,"Complete",IF(F6=0,"Not Started","In Progress")) -> Not Started | I6: 1.0 hr concept + 2.5 hrs solving 5 class Qs + 1.0 hr pattern recap + 0.5 hr HW briefing
A7: 5 | B7: Sliding Window - Variable Size | C7: CF 1200-1400 | D7: =COUNTIFS(Tracker!$A:$A,5,Tracker!$B:$B,"In-Class",Tracker!$J:$J,"Solved") -> 0 | E7: =COUNTIFS(Tracker!$A:$A,5,Tracker!$B:$B,"Homework",Tracker!$J:$J,"Solved") -> 0 | F7: =D7+E7 -> 0 | G7: =ROUND(F7/15*100,0)&"%" -> 0% | H7: =IF(F7=15,"Complete",IF(F7=0,"Not Started","In Progress")) -> Not Started | I7: 1.0 hr concept + 2.5 hrs solving 5 class Qs + 1.0 hr pattern recap + 0.5 hr HW briefing
A8: 6 | B8: Hashing & Frequency Maps | C8: HR Easy-Med / CF 1100-1400 | D8: =COUNTIFS(Tracker!$A:$A,6,Tracker!$B:$B,"In-Class",Tracker!$J:$J,"Solved") -> 0 | E8: =COUNTIFS(Tracker!$A:$A,6,Tracker!$B:$B,"Homework",Tracker!$J:$J,"Solved") -> 0 | F8: =D8+E8 -> 0 | G8: =ROUND(F8/15*100,0)&"%" -> 0% | H8: =IF(F8=15,"Complete",IF(F8=0,"Not Started","In Progress")) -> Not Started | I8: 1.0 hr concept + 2.5 hrs solving 5 class Qs + 1.0 hr pattern recap + 0.5 hr HW briefing
A9: 7 | B9: Strings I - Scanning & Transformation | C9: HR Easy / CF 800-1000 | D9: =COUNTIFS(Tracker!$A:$A,7,Tracker!$B:$B,"In-Class",Tracker!$J:$J,"Solved") -> 0 | E9: =COUNTIFS(Tracker!$A:$A,7,Tracker!$B:$B,"Homework",Tracker!$J:$J,"Solved") -> 0 | F9: =D9+E9 -> 0 | G9: =ROUND(F9/15*100,0)&"%" -> 0% | H9: =IF(F9=15,"Complete",IF(F9=0,"Not Started","In Progress")) -> Not Started | I9: 1.0 hr concept + 2.5 hrs solving 5 class Qs + 1.0 hr pattern recap + 0.5 hr HW briefing
A10: 8 | B10: Strings II - Anagrams & Palindromes | C10: HR Easy-Med / CF 1000-1300 | D10: =COUNTIFS(Tracker!$A:$A,8,Tracker!$B:$B,"In-Class",Tracker!$J:$J,"Solved") -> 0 | E10: =COUNTIFS(Tracker!$A:$A,8,Tracker!$B:$B,"Homework",Tracker!$J:$J,"Solved") -> 0 | F10: =D10+E10 -> 0 | G10: =ROUND(F10/15*100,0)&"%" -> 0% | H10: =IF(F10=15,"Complete",IF(F10=0,"Not Started","In Progress")) -> Not Started | I10: 1.0 hr concept + 2.5 hrs solving 5 class Qs + 1.0 hr pattern recap + 0.5 hr HW briefing
A11: 9 | B11: Sorting I - Ordering & Comparators | C11: HR Easy / CF 800-1100 | D11: =COUNTIFS(Tracker!$A:$A,9,Tracker!$B:$B,"In-Class",Tracker!$J:$J,"Solved") -> 0 | E11: =COUNTIFS(Tracker!$A:$A,9,Tracker!$B:$B,"Homework",Tracker!$J:$J,"Solved") -> 0 | F11: =D11+E11 -> 0 | G11: =ROUND(F11/15*100,0)&"%" -> 0% | H11: =IF(F11=15,"Complete",IF(F11=0,"Not Started","In Progress")) -> Not Started | I11: 1.0 hr concept + 2.5 hrs solving 5 class Qs + 1.0 hr pattern recap + 0.5 hr HW briefing
A12: 10 | B12: Sorting II - Counting Sort & Order Statistics | C12: HR Med-Hard / CF 1100-1300 | D12: =COUNTIFS(Tracker!$A:$A,10,Tracker!$B:$B,"In-Class",Tracker!$J:$J,"Solved") -> 0 | E12: =COUNTIFS(Tracker!$A:$A,10,Tracker!$B:$B,"Homework",Tracker!$J:$J,"Solved") -> 0 | F12: =D12+E12 -> 0 | G12: =ROUND(F12/15*100,0)&"%" -> 0% | H12: =IF(F12=15,"Complete",IF(F12=0,"Not Started","In Progress")) -> Not Started | I12: 1.0 hr concept + 2.5 hrs solving 5 class Qs + 1.0 hr pattern recap + 0.5 hr HW briefing
A13: 11 | B13: Binary Search I - On Sorted Data | C13: HR Easy / CF 800-1200 | D13: =COUNTIFS(Tracker!$A:$A,11,Tracker!$B:$B,"In-Class",Tracker!$J:$J,"Solved") -> 0 | E13: =COUNTIFS(Tracker!$A:$A,11,Tracker!$B:$B,"Homework",Tracker!$J:$J,"Solved") -> 0 | F13: =D13+E13 -> 0 | G13: =ROUND(F13/15*100,0)&"%" -> 0% | H13: =IF(F13=15,"Complete",IF(F13=0,"Not Started","In Progress")) -> Not Started | I13: 1.0 hr concept + 2.5 hrs solving 5 class Qs + 1.0 hr pattern recap + 0.5 hr HW briefing
A14: 12 | B14: Binary Search on the Answer | C14: HR Med / CF 1200-1500 | D14: =COUNTIFS(Tracker!$A:$A,12,Tracker!$B:$B,"In-Class",Tracker!$J:$J,"Solved") -> 0 | E14: =COUNTIFS(Tracker!$A:$A,12,Tracker!$B:$B,"Homework",Tracker!$J:$J,"Solved") -> 0 | F14: =D14+E14 -> 0 | G14: =ROUND(F14/15*100,0)&"%" -> 0% | H14: =IF(F14=15,"Complete",IF(F14=0,"Not Started","In Progress")) -> Not Started | I14: 1.0 hr concept + 2.5 hrs solving 5 class Qs + 1.0 hr pattern recap + 0.5 hr HW briefing
A15: 13 | B15: Greedy I - Local Choices | C15: HR Easy / CF 800-1000 | D15: =COUNTIFS(Tracker!$A:$A,13,Tracker!$B:$B,"In-Class",Tracker!$J:$J,"Solved") -> 0 | E15: =COUNTIFS(Tracker!$A:$A,13,Tracker!$B:$B,"Homework",Tracker!$J:$J,"Solved") -> 0 | F15: =D15+E15 -> 0 | G15: =ROUND(F15/15*100,0)&"%" -> 0% | H15: =IF(F15=15,"Complete",IF(F15=0,"Not Started","In Progress")) -> Not Started | I15: 1.0 hr concept + 2.5 hrs solving 5 class Qs + 1.0 hr pattern recap + 0.5 hr HW briefing
A16: 14 | B16: Greedy II - Sorting-Based & Interval Greedy | C16: HR Easy-Med / CF 1100-1300 | D16: =COUNTIFS(Tracker!$A:$A,14,Tracker!$B:$B,"In-Class",Tracker!$J:$J,"Solved") -> 0 | E16: =COUNTIFS(Tracker!$A:$A,14,Tracker!$B:$B,"Homework",Tracker!$J:$J,"Solved") -> 0 | F16: =D16+E16 -> 0 | G16: =ROUND(F16/15*100,0)&"%" -> 0% | H16: =IF(F16=15,"Complete",IF(F16=0,"Not Started","In Progress")) -> Not Started | I16: 1.0 hr concept + 2.5 hrs solving 5 class Qs + 1.0 hr pattern recap + 0.5 hr HW briefing
A17: 15 | B17: Math I - Arithmetic & Counting | C17: CF 800-1000 | D17: =COUNTIFS(Tracker!$A:$A,15,Tracker!$B:$B,"In-Class",Tracker!$J:$J,"Solved") -> 0 | E17: =COUNTIFS(Tracker!$A:$A,15,Tracker!$B:$B,"Homework",Tracker!$J:$J,"Solved") -> 0 | F17: =D17+E17 -> 0 | G17: =ROUND(F17/15*100,0)&"%" -> 0% | H17: =IF(F17=15,"Complete",IF(F17=0,"Not Started","In Progress")) -> Not Started | I17: 1.0 hr concept + 2.5 hrs solving 5 class Qs + 1.0 hr pattern recap + 0.5 hr HW briefing
A18: 16 | B18: Math II - Number Theory (GCD, Primes, Modulo) | C18: CF 1000-1300 | D18: =COUNTIFS(Tracker!$A:$A,16,Tracker!$B:$B,"In-Class",Tracker!$J:$J,"Solved") -> 0 | E18: =COUNTIFS(Tracker!$A:$A,16,Tracker!$B:$B,"Homework",Tracker!$J:$J,"Solved") -> 0 | F18: =D18+E18 -> 0 | G18: =ROUND(F18/15*100,0)&"%" -> 0% | H18: =IF(F18=15,"Complete",IF(F18=0,"Not Started","In Progress")) -> Not Started | I18: 1.0 hr concept + 2.5 hrs solving 5 class Qs + 1.0 hr pattern recap + 0.5 hr HW briefing
A19: 17 | B19: Bit Manipulation & XOR | C19: HR Easy-Med / CF 800-1300 | D19: =COUNTIFS(Tracker!$A:$A,17,Tracker!$B:$B,"In-Class",Tracker!$J:$J,"Solved") -> 0 | E19: =COUNTIFS(Tracker!$A:$A,17,Tracker!$B:$B,"Homework",Tracker!$J:$J,"Solved") -> 0 | F19: =D19+E19 -> 0 | G19: =ROUND(F19/15*100,0)&"%" -> 0% | H19: =IF(F19=15,"Complete",IF(F19=0,"Not Started","In Progress")) -> Not Started | I19: 1.0 hr concept + 2.5 hrs solving 5 class Qs + 1.0 hr pattern recap + 0.5 hr HW briefing
A20: 18 | B20: Recursion & Complete Search | C20: HR Easy-Med / CF 800-1100 | D20: =COUNTIFS(Tracker!$A:$A,18,Tracker!$B:$B,"In-Class",Tracker!$J:$J,"Solved") -> 0 | E20: =COUNTIFS(Tracker!$A:$A,18,Tracker!$B:$B,"Homework",Tracker!$J:$J,"Solved") -> 0 | F20: =D20+E20 -> 0 | G20: =ROUND(F20/15*100,0)&"%" -> 0% | H20: =IF(F20=15,"Complete",IF(F20=0,"Not Started","In Progress")) -> Not Started | I20: 1.0 hr concept + 2.5 hrs solving 5 class Qs + 1.0 hr pattern recap + 0.5 hr HW briefing
A21: 19 | B21: Backtracking & Constructive Algorithms | C21: HR Med / CF 1000-1300 | D21: =COUNTIFS(Tracker!$A:$A,19,Tracker!$B:$B,"In-Class",Tracker!$J:$J,"Solved") -> 0 | E21: =COUNTIFS(Tracker!$A:$A,19,Tracker!$B:$B,"Homework",Tracker!$J:$J,"Solved") -> 0 | F21: =D21+E21 -> 0 | G21: =ROUND(F21/15*100,0)&"%" -> 0% | H21: =IF(F21=15,"Complete",IF(F21=0,"Not Started","In Progress")) -> Not Started | I21: 1.0 hr concept + 2.5 hrs solving 5 class Qs + 1.0 hr pattern recap + 0.5 hr HW briefing
A22: 20 | B22: Linked Lists - Pointers in Motion | C22: HR Easy-Med | D22: =COUNTIFS(Tracker!$A:$A,20,Tracker!$B:$B,"In-Class",Tracker!$J:$J,"Solved") -> 0 | E22: =COUNTIFS(Tracker!$A:$A,20,Tracker!$B:$B,"Homework",Tracker!$J:$J,"Solved") -> 0 | F22: =D22+E22 -> 0 | G22: =ROUND(F22/15*100,0)&"%" -> 0% | H22: =IF(F22=15,"Complete",IF(F22=0,"Not Started","In Progress")) -> Not Started | I22: 1.0 hr concept + 2.5 hrs solving 5 class Qs + 1.0 hr pattern recap + 0.5 hr HW briefing
A23: 21 | B23: Stacks - LIFO Thinking | C23: HR Easy-Med / CF 1000-1300 | D23: =COUNTIFS(Tracker!$A:$A,21,Tracker!$B:$B,"In-Class",Tracker!$J:$J,"Solved") -> 0 | E23: =COUNTIFS(Tracker!$A:$A,21,Tracker!$B:$B,"Homework",Tracker!$J:$J,"Solved") -> 0 | F23: =D23+E23 -> 0 | G23: =ROUND(F23/15*100,0)&"%" -> 0% | H23: =IF(F23=15,"Complete",IF(F23=0,"Not Started","In Progress")) -> Not Started | I23: 1.0 hr concept + 2.5 hrs solving 5 class Qs + 1.0 hr pattern recap + 0.5 hr HW briefing
A24: 22 | B24: Monotonic Stack - Next Greater / Spans | C24: HR Med-Hard / CF 1100-1400 | D24: =COUNTIFS(Tracker!$A:$A,22,Tracker!$B:$B,"In-Class",Tracker!$J:$J,"Solved") -> 0 | E24: =COUNTIFS(Tracker!$A:$A,22,Tracker!$B:$B,"Homework",Tracker!$J:$J,"Solved") -> 0 | F24: =D24+E24 -> 0 | G24: =ROUND(F24/15*100,0)&"%" -> 0% | H24: =IF(F24=15,"Complete",IF(F24=0,"Not Started","In Progress")) -> Not Started | I24: 1.0 hr concept + 2.5 hrs solving 5 class Qs + 1.0 hr pattern recap + 0.5 hr HW briefing
A25: 23 | B25: Queues & Deques - FIFO and Both-End Access | C25: HR Med / CF 1100-1400 | D25: =COUNTIFS(Tracker!$A:$A,23,Tracker!$B:$B,"In-Class",Tracker!$J:$J,"Solved") -> 0 | E25: =COUNTIFS(Tracker!$A:$A,23,Tracker!$B:$B,"Homework",Tracker!$J:$J,"Solved") -> 0 | F25: =D25+E25 -> 0 | G25: =ROUND(F25/15*100,0)&"%" -> 0% | H25: =IF(F25=15,"Complete",IF(F25=0,"Not Started","In Progress")) -> Not Started | I25: 1.0 hr concept + 2.5 hrs solving 5 class Qs + 1.0 hr pattern recap + 0.5 hr HW briefing
A26: 24 | B26: Heaps & Priority Queues | C26: HR Easy-Hard / CF 1200-1500 | D26: =COUNTIFS(Tracker!$A:$A,24,Tracker!$B:$B,"In-Class",Tracker!$J:$J,"Solved") -> 0 | E26: =COUNTIFS(Tracker!$A:$A,24,Tracker!$B:$B,"Homework",Tracker!$J:$J,"Solved") -> 0 | F26: =D26+E26 -> 0 | G26: =ROUND(F26/15*100,0)&"%" -> 0% | H26: =IF(F26=15,"Complete",IF(F26=0,"Not Started","In Progress")) -> Not Started | I26: 1.0 hr concept + 2.5 hrs solving 5 class Qs + 1.0 hr pattern recap + 0.5 hr HW briefing
A27: 25 | B27: Trees I - Traversals & Views | C27: HR Easy-Med / CF 1000-1300 | D27: =COUNTIFS(Tracker!$A:$A,25,Tracker!$B:$B,"In-Class",Tracker!$J:$J,"Solved") -> 0 | E27: =COUNTIFS(Tracker!$A:$A,25,Tracker!$B:$B,"Homework",Tracker!$J:$J,"Solved") -> 0 | F27: =D27+E27 -> 0 | G27: =ROUND(F27/15*100,0)&"%" -> 0% | H27: =IF(F27=15,"Complete",IF(F27=0,"Not Started","In Progress")) -> Not Started | I27: 1.0 hr concept + 2.5 hrs solving 5 class Qs + 1.0 hr pattern recap + 0.5 hr HW briefing
A28: 26 | B28: Trees II - BST & Structural Properties | C28: HR Easy-Med / CF 1300-1500 | D28: =COUNTIFS(Tracker!$A:$A,26,Tracker!$B:$B,"In-Class",Tracker!$J:$J,"Solved") -> 0 | E28: =COUNTIFS(Tracker!$A:$A,26,Tracker!$B:$B,"Homework",Tracker!$J:$J,"Solved") -> 0 | F28: =D28+E28 -> 0 | G28: =ROUND(F28/15*100,0)&"%" -> 0% | H28: =IF(F28=15,"Complete",IF(F28=0,"Not Started","In Progress")) -> Not Started | I28: 1.0 hr concept + 2.5 hrs solving 5 class Qs + 1.0 hr pattern recap + 0.5 hr HW briefing
A29: 27 | B29: Graphs I - BFS & Shortest Reach | C29: HR Med / CF 1000-1300 | D29: =COUNTIFS(Tracker!$A:$A,27,Tracker!$B:$B,"In-Class",Tracker!$J:$J,"Solved") -> 0 | E29: =COUNTIFS(Tracker!$A:$A,27,Tracker!$B:$B,"Homework",Tracker!$J:$J,"Solved") -> 0 | F29: =D29+E29 -> 0 | G29: =ROUND(F29/15*100,0)&"%" -> 0% | H29: =IF(F29=15,"Complete",IF(F29=0,"Not Started","In Progress")) -> Not Started | I29: 1.0 hr concept + 2.5 hrs solving 5 class Qs + 1.0 hr pattern recap + 0.5 hr HW briefing
A30: 28 | B30: Graphs II - DFS & Connected Components | C30: HR Med / CF 1100-1400 | D30: =COUNTIFS(Tracker!$A:$A,28,Tracker!$B:$B,"In-Class",Tracker!$J:$J,"Solved") -> 0 | E30: =COUNTIFS(Tracker!$A:$A,28,Tracker!$B:$B,"Homework",Tracker!$J:$J,"Solved") -> 0 | F30: =D30+E30 -> 0 | G30: =ROUND(F30/15*100,0)&"%" -> 0% | H30: =IF(F30=15,"Complete",IF(F30=0,"Not Started","In Progress")) -> Not Started | I30: 1.0 hr concept + 2.5 hrs solving 5 class Qs + 1.0 hr pattern recap + 0.5 hr HW briefing
A31: 29 | B31: Union-Find (DSU) & Minimum Spanning Trees | C31: HR Med / CF 1100-1500 | D31: =COUNTIFS(Tracker!$A:$A,29,Tracker!$B:$B,"In-Class",Tracker!$J:$J,"Solved") -> 0 | E31: =COUNTIFS(Tracker!$A:$A,29,Tracker!$B:$B,"Homework",Tracker!$J:$J,"Solved") -> 0 | F31: =D31+E31 -> 0 | G31: =ROUND(F31/15*100,0)&"%" -> 0% | H31: =IF(F31=15,"Complete",IF(F31=0,"Not Started","In Progress")) -> Not Started | I31: 1.0 hr concept + 2.5 hrs solving 5 class Qs + 1.0 hr pattern recap + 0.5 hr HW briefing
A32: 30 | B32: Weighted Shortest Paths - Dijkstra & Friends | C32: HR Med / CF 1200-1600 | D32: =COUNTIFS(Tracker!$A:$A,30,Tracker!$B:$B,"In-Class",Tracker!$J:$J,"Solved") -> 0 | E32: =COUNTIFS(Tracker!$A:$A,30,Tracker!$B:$B,"Homework",Tracker!$J:$J,"Solved") -> 0 | F32: =D32+E32 -> 0 | G32: =ROUND(F32/15*100,0)&"%" -> 0% | H32: =IF(F32=15,"Complete",IF(F32=0,"Not Started","In Progress")) -> Not Started | I32: 1.0 hr concept + 2.5 hrs solving 5 class Qs + 1.0 hr pattern recap + 0.5 hr HW briefing
A33: 31 | B33: Dynamic Programming I - 1D States | C33: HR Med / CF 1000-1300 | D33: =COUNTIFS(Tracker!$A:$A,31,Tracker!$B:$B,"In-Class",Tracker!$J:$J,"Solved") -> 0 | E33: =COUNTIFS(Tracker!$A:$A,31,Tracker!$B:$B,"Homework",Tracker!$J:$J,"Solved") -> 0 | F33: =D33+E33 -> 0 | G33: =ROUND(F33/15*100,0)&"%" -> 0% | H33: =IF(F33=15,"Complete",IF(F33=0,"Not Started","In Progress")) -> Not Started | I33: 1.0 hr concept + 2.5 hrs solving 5 class Qs + 1.0 hr pattern recap + 0.5 hr HW briefing
A34: 32 | B34: Dynamic Programming II - Grids & Knapsack + Big-O Capstone | C34: HR Med-Hard / CF 1300-1600 | D34: =COUNTIFS(Tracker!$A:$A,32,Tracker!$B:$B,"In-Class",Tracker!$J:$J,"Solved") -> 0 | E34: =COUNTIFS(Tracker!$A:$A,32,Tracker!$B:$B,"Homework",Tracker!$J:$J,"Solved") -> 0 | F34: =D34+E34 -> 0 | G34: =ROUND(F34/15*100,0)&"%" -> 0% | H34: =IF(F34=15,"Complete",IF(F34=0,"Not Started","In Progress")) -> Not Started | I34: 1.0 hr concept + 2.5 hrs solving 5 class Qs + 1.0 hr pattern recap + 0.5 hr HW briefing

Sheet Pattern Guide
A1: PATTERN GUIDE - What It Is, How to Spot It, Why Problems Belong
A2: Class # | B2: Pattern / Topic | C2: What It Is | D2: How to Spot It in a Problem | E2: Why the Assigned Problems Belong Here
A3: 1 | B3: Arrays & Implementation Basics | C3: Storing and manipulating fixed-order data: traversal, rotation, insertion, in-place updates. | D3: Input is a list/grid; task asks to read, rotate, update, or simulate steps exactly as described. | E3: Pure array traversal / simulation - the solution is careful index handling, no advanced algorithm needed.
A4: 2 | B4: Prefix Sums & Difference Arrays | C4: Precompute running totals so any range-sum query answers in O(1); difference arrays apply range updates in O(1). | D4: Repeated queries like 'sum of L..R', 'add x to a range', or balance-point questions on static arrays. | E4: Range-sum / range-update structure - prefix or difference array turns O(n) per query into O(1).
A5: 3 | B5: Two Pointers I - Converging & Parallel Scans | C5: Two indices moving through data (toward each other or in the same direction) to avoid nested loops. | D5: Sorted input, pair-finding, merging, or 'can we match elements from both ends?' style statements. | E5: Two coordinated indices replace an O(n^2) pair search with a single O(n) sweep.
A6: 4 | B6: Sliding Window - Fixed Size | C6: Maintain a window of exactly k elements; slide by adding one element and removing one - O(n) totals. | D6: 'Every subarray of length k', 'k consecutive days/items', max/min/sum over fixed-width blocks. | E6: Fixed-width consecutive block - sliding the window updates the answer in O(1) per step.
A7: 5 | B7: Sliding Window - Variable Size | C7: Grow the right end while a condition holds, shrink from the left when it breaks - window size adapts. | D7: 'Longest/shortest subarray such that ...' with a monotone condition (sum, distinct count, at most k). | E7: Expand-shrink window logic - the constraint is monotone, so each pointer moves only forward.
A8: 6 | B8: Hashing & Frequency Maps | C8: Hash maps/sets give O(1) average lookup - count frequencies, detect duplicates, match complements. | D8: How many times', 'does a pair/anagram exist', 'first non-repeating' - membership or count questions. | E8: Counting / membership question - a frequency map answers 'seen before? how often?' in O(1).
A9: 7 | B9: Strings I - Scanning & Transformation | C9: Character-by-character processing: case rules, shifts, validation, building new strings. | D9: Task describes a rule applied to each character or a format the string must satisfy. | E9: Linear character scan - apply the stated rule per character; ASCII arithmetic does the work.
A10: 8 | B10: Strings II - Anagrams & Palindromes | C10: Structural string properties: anagram = same letter multiset; palindrome = mirror symmetry. | D10: 'Make these anagrams', 'minimum deletions/changes', 'reads the same backwards'. | E10: Anagram/palindrome structure - compare frequency multisets or mirrored index pairs.
A11: 9 | B11: Sorting I - Ordering & Comparators | C11: Reordering data unlocks greedy scans, pairing, and binary search; custom comparators define 'order'. | D11: Answer depends only on relative order, closest pairs, or arranging to maximize/minimize something. | E11: Sort-first problem - once ordered, the answer falls out of one linear pass.
A12: 10 | B12: Sorting II - Counting Sort & Order Statistics | C12: Non-comparison sorting (counting sort), medians, inversion counting via merge sort. | D12: Small value range (counting sort), running median, or 'how far from sorted' questions. | E12: Order-statistic / stable-count structure - counting sort or merge logic beats plain sorting.
A13: 11 | B13: Binary Search I - On Sorted Data | C13: Halve the search space each step on sorted/monotone data - O(log n) lookups and boundaries. | D13: Sorted input plus 'find position / first / last / closest' questions. | E13: Sorted-search structure - each comparison discards half the candidates.
A14: 12 | B14: Binary Search on the Answer | C14: When 'can we achieve X?' is monotone in X, binary-search X itself and check feasibility. | D14: Minimize the maximum / maximize the minimum; 'least time/capacity/distance so that ...'. | E14: Monotone feasibility - check(X) flips once from false to true, so binary search finds the boundary.
... A34: 32 | B34: Dynamic Programming II - Grids & Knapsack + Big-O Capstone | C34: 2D/knapsack DP: grid paths, subset sums, coin change; then complexity analysis across all 32 patterns as the course capstone. | D34: Two changing quantities (index + capacity), grid movement, or 'choose items under a budget'. | E34: Multi-dimensional DP - the state needs two coordinates; capstone: justify the Big-O of every pattern learned.

Sheet Tracker
A1: Class # | B1: Session Type | C1: Q # | D1: Pattern / Topic | E1: Problem | F1: Platform | G1: Difficulty | H1: Problem Link | I1: Why This Pattern | J1: Status | K1: Notes
A2: 1 | B2: In-Class | C2: 1 | D2: Arrays & Implementation Basics | E2: 158A - Next Round | F2: Codeforces | G2: CF 800 | H2: Open Problem | I2: Pure array traversal / simulation - the solution is careful index handling, no advanced algorithm needed. (CF tags: *special problem, implementation) | J2: Solved | K2: Example - pattern clicked after drawing it out
A3: 1 | B3: In-Class | C3: 2 | D3: Arrays & Implementation Basics | E3: 282A - Bit++ | F3: Codeforces | G3: CF 800 | H3: Open Problem | I3: Pure array traversal / simulation - the solution is careful index handling, no advanced algorithm needed. (CF tags: implementation) | J3: Solved
A4: 1 | B4: In-Class | C4: 3 | D4: Arrays & Implementation Basics | E4: 263A - Beautiful Matrix | F4: Codeforces | G4: CF 800 | H4: Open Problem | I4: Pure array traversal / simulation - the solution is careful index handling, no advanced algorithm needed. (CF tags: implementation) | J4: Solved
A5: 1 | B5: In-Class | C5: 4 | D5: Arrays & Implementation Basics | E5: 266A - Stones on the Table | F5: Codeforces | G5: CF 800 | H5: Open Problem | I5: Pure array traversal / simulation - the solution is careful index handling, no advanced algorithm needed. (CF tags: implementation) | J5: Solved
A6: 1 | B6: In-Class | C6: 5 | D6: Arrays & Implementation Basics | E6: 791A - Bear and Big Brother | F6: Codeforces | G6: CF 800 | H6: Open Problem | I6: Pure array traversal / simulation - the solution is careful index handling, no advanced algorithm needed. (CF tags: implementation) | J6: Solved
A7: 1 | B7: Homework | C7: 1 | D7: Arrays & Implementation Basics | E7: 546A - Soldier and Bananas | F7: Codeforces | G7: CF 800 | H7: Open Problem | I7: Pure array traversal / simulation - the solution is careful index handling, no advanced algorithm needed. (CF tags: brute force, implementation, math) | J7: Solved
A8: 1 | B8: Homework | C8: 2 | D8: Arrays & Implementation Basics | E8: 977A - Wrong Subtraction | F8: Codeforces | G8: CF 800 | H8: Open Problem | I8: Pure array traversal / simulation - the solution is careful index handling, no advanced algorithm needed. (CF tags: implementation) | J8: Solved
A9: 1 | B9: Homework | C9: 3 | D9: Arrays & Implementation Basics | E9: 110A - Nearly Lucky Number | F9: Codeforces | G9: CF 800 | H9: Open Problem | I9: Pure array traversal / simulation - the solution is careful index handling, no advanced algorithm needed. (CF tags: implementation) | J9: Solved
A10: 1 | B10: Homework | C10: 4 | D10: Arrays & Implementation Basics | E10: Arrays - DS | F10: HackerRank | G10: HR Easy | H10: Open Problem | I10: Pure array traversal / simulation - the solution is careful index handling, no advanced algorithm needed. | J10: Solved
A11: 1 | B11: Homework | C11: 5 | D11: Arrays & Implementation Basics | E11: 2D Array - DS (Hourglass Sum) | F11: HackerRank | G11: HR Easy | H11: Open Problem | I11: Pure array traversal / simulation - the solution is careful index handling, no advanced algorithm needed. | J11: Solved
A12: 1 | B12: Homework | C12: 6 | D12: Arrays & Implementation Basics | E12: Arrays: Left Rotation | F12: HackerRank | G12: HR Easy | H12: Open Problem | I12: Pure array traversal / simulation - the solution is careful index handling, no advanced algorithm needed. | J12: Solved
A13: 1 | B13: Homework | C13: 7 | D13: Arrays & Implementation Basics | E13: Dynamic Array | F13: HackerRank | G13: HR Easy | H13: Open Problem | I13: Pure array traversal / simulation - the solution is careful index handling, no advanced algorithm needed. | J13: Not Started
A14: 1 | B14: Homework | C14: 8 | D14: Arrays & Implementation Basics | E14: Missing Numbers | F14: HackerRank | G14: HR Easy | H14: Open Problem | I14: Pure array traversal / simulation - the solution is careful index handling, no advanced algorithm needed. | J14: Not Started
... A481: 32 | B481: Homework | C481: 10 | D481: Dynamic Programming II - Grids & Knapsack + Big-O Capstone | E481: 1526B - I Hate 1111 | F481: Codeforces | G481: CF 1400 | H481: Open Problem | I481: Multi-dimensional DP - the state needs two coordinates; capstone: justify the Big-O of every pattern learned. (CF tags: dp, math, number theory) | J481: Not Started
